yt_whisper/__init__.py
yt_whisper/__main__.py
yt_whisper/cli.py
yt_whisper/db.py
yt_whisper/lib.py
yt_whisper/storage.py
yt_whisper-1.0.2.dist-info/licenses/LICENSE
yt_whisper-1.0.2.dist-info/METADATA
yt_whisper-1.0.2.dist-info/WHEEL
yt_whisper-1.0.2.dist-info/entry_points.txt
yt_whisper-1.0.2.dist-info/top_level.txt
yt_whisper-1.0.2.dist-info/RECORD
