Metadata-Version: 2.4
Name: yt-whisper
Version: 1.0.2
Summary: Download and transcribe YouTube videos using Whisper
Author-email: Pål Østerud <pypi@paal.dk>
License: Apache License, Version 2.0
Project-URL: Homepage, https://github.com/paos/yt-whisper
Project-URL: Issues, https://github.com/paos/yt-whisper/issues
Project-URL: CI, https://github.com/paos/yt-whisper/actions
Project-URL: Changelog, https://github.com/paos/yt-whisper/releases
Requires-Python: >=3.10
License-File: LICENSE
Requires-Dist: click>=8.2.0
Requires-Dist: openai-whisper>=20231117
Requires-Dist: platformdirs>=4.3.8
Requires-Dist: yt-dlp>=2023.12.30
Provides-Extra: dev
Requires-Dist: pre-commit>=4.2.0; extra == "dev"
Requires-Dist: pytest>=8.3.5; extra == "dev"
Requires-Dist: pytest-cov>=4.1.0; extra == "dev"
Requires-Dist: ruff>=0.11.9; extra == "dev"
Requires-Dist: setuptools>=80.4.0; extra == "dev"
Requires-Dist: setuptools-scm>=8.3.1; extra == "dev"
Provides-Extra: test
Requires-Dist: pytest>=8.3.5; extra == "test"
Requires-Dist: pytest-cov>=4.1.0; extra == "test"
Dynamic: license-file
